{
  "schema_version": "0.1",
  "artifact_id": "HAD95_3579_1",
  "artifact_class": "pottery",
  "image": {
    "image_filename": "HAD95_3579_1__phi_180__theta_140.png",
    "image_path": "C:\\Users\\netta\\OneDrive\\Documents\\Coding Projects\\3D renderer and segmenter\\output\\images\\unclassified\\HAD95_3579_1\\HAD95_3579_1__phi_180__theta_140.png",
    "angle_metadata": {
      "phi": 180,
      "theta": 140,
      "elevation": null
    },
    "width": 512,
    "height": 512,
    "annotated_file": "C:\\Users\\netta\\OneDrive\\Documents\\Coding Projects\\3D renderer and segmenter\\output\\segmenter\\HAD95_3579_1\\annotated\\HAD95_3579_1_phi_180_theta_140__annotated.png",
    "clean_visual_file": "C:\\Users\\netta\\OneDrive\\Documents\\Coding Projects\\3D renderer and segmenter\\output\\segmenter\\HAD95_3579_1\\clean_visual\\HAD95_3579_1_phi_180_theta_140__clean.png",
    "parts": [
      {
        "part_name": "rim",
        "confidence": 0.565,
        "low_confidence": false,
        "quality_score": 0.7034,
        "bbox_xywh": [
          148,
          157,
          197,
          34
        ],
        "mask_area_px": 4607,
        "mask_rle": {
          "size": [
            512,
            512
          ],
          "counts": [
            75966,
            1,
            510,
            2,
            510,
            2,
            509,
            3,
            508,
            4,
            508,
            4,
            507,
            5,
            506,
            6,
            506,
            6,
            505,
            7,
            505,
            7,
            504,
            8,
            503,
            9,
            503,
            9,
            502,
            10,
            501,
            11,
            501,
            11,
            500,
            12,
            500,
            12,
            499,
            13,
            499,
            13,
            498,
            14,
            498,
            14,
            497,
            15,
            497,
            15,
            496,
            16,
            496,
            16,
            495,
            17,
            495,
            17,
            494,
            18,
            493,
            19,
            493,
            19,
            493,
            19,
            492,
            20,
            492,
            20,
            491,
            21,
            491,
            21,
            490,
            22,
            490,
            22,
            490,
            22,
            489,
            23,
            489,
            23,
            489,
            23,
            488,
            24,
            488,
            24,
            487,
            25,
            487,
            25,
            487,
            25,
            486,
            26,
            486,
            26,
            486,
            26,
            485,
            27,
            485,
            27,
            485,
            27,
            484,
            28,
            484,
            28,
            484,
            28,
            484,
            28,
            483,
            29,
            483,
            29,
            483,
            29,
            483,
            29,
            482,
            30,
            482,
            30,
            482,
            30,
            482,
            30,
            481,
            31,
            481,
            31,
            481,
            31,
            481,
            31,
            481,
            31,
            480,
            32,
            480,
            32,
            480,
            32,
            480,
            32,
            480,
            32,
            480,
            32,
            480,
            32,
            479,
            33,
            479,
            33,
            479,
            33,
            479,
            33,
            479,
            33,
            479,
            33,
            479,
            33,
            479,
            33,
            478,
            34,
            478,
            34,
            478,
            34,
            478,
            34,
            478,
            34,
            478,
            34,
            478,
            34,
            478,
            34,
            478,
            34,
            478,
            34,
            478,
            34,
            478,
            34,
            478,
            34,
            478,
            34,
            478,
            34,
            478,
            34,
            478,
            34,
            478,
            34,
            478,
            34,
            478,
            34,
            478,
            34,
            478,
            34,
            478,
            34,
            478,
            34,
            478,
            34,
            478,
            34,
            479,
            33,
            479,
            33,
            479,
            33,
            479,
            33,
            479,
            33,
            479,
            33,
            479,
            33,
            479,
            33,
            479,
            33,
            479,
            33,
            480,
            32,
            480,
            32,
            480,
            32,
            480,
            32,
            480,
            32,
            480,
            32,
            481,
            31,
            481,
            31,
            481,
            31,
            481,
            31,
            481,
            31,
            481,
            31,
            482,
            30,
            482,
            30,
            482,
            30,
            482,
            30,
            483,
            29,
            483,
            29,
            483,
            29,
            483,
            29,
            484,
            28,
            484,
            28,
            484,
            28,
            484,
            28,
            485,
            27,
            485,
            27,
            485,
            27,
            486,
            26,
            486,
            26,
            486,
            26,
            487,
            25,
            487,
            25,
            487,
            25,
            488,
            24,
            488,
            24,
            488,
            24,
            489,
            23,
            489,
            23,
            490,
            22,
            490,
            22,
            491,
            21,
            491,
            21,
            492,
            20,
            492,
            20,
            492,
            20,
            493,
            19,
            493,
            19,
            494,
            18,
            494,
            18,
            495,
            17,
            495,
            17,
            496,
            16,
            496,
            16,
            497,
            15,
            498,
            14,
            498,
            14,
            499,
            13,
            499,
            13,
            500,
            12,
            500,
            12,
            501,
            11,
            502,
            10,
            502,
            10,
            503,
            9,
            504,
            8,
            504,
            8,
            505,
            7,
            506,
            6,
            506,
            6,
            507,
            5,
            508,
            4,
            509,
            3,
            510,
            2,
            510,
            2,
            511,
            1,
            85825
          ],
          "format": "uncompressed_rle"
        },
        "method": "geometric_taxonomy",
        "crop_file": "C:\\Users\\netta\\OneDrive\\Documents\\Coding Projects\\3D renderer and segmenter\\output\\segmenter\\HAD95_3579_1\\part_crops\\rim\\HAD95_3579_1_phi_180_theta_140__rim.png"
      },
      {
        "part_name": "neck",
        "confidence": 0.6721,
        "low_confidence": false,
        "quality_score": 0.836,
        "bbox_xywh": [
          144,
          191,
          226,
          46
        ],
        "mask_area_px": 8895,
        "mask_rle": {
          "size": [
            512,
            512
          ],
          "counts": [
            73921,
            5,
            507,
            7,
            504,
            10,
            501,
            12,
            500,
            12,
            500,
            12,
            500,
            12,
            500,
            12,
            500,
            12,
            500,
            12,
            500,
            13,
            499,
            13,
            499,
            13,
            499,
            13,
            499,
            13,
            30,
            3,
            466,
            13,
            28,
            5,
            466,
            13,
            25,
            8,
            466,
            13,
            23,
            10,
            466,
            14,
            19,
            13,
            466,
            14,
            17,
            15,
            466,
            14,
            15,
            17,
            466,
            14,
            14,
            18,
            466,
            14,
            12,
            20,
            466,
            14,
            9,
            23,
            466,
            46,
            466,
            46,
            466,
            46,
            466,
            46,
            466,
            46,
            466,
            46,
            466,
            46,
            466,
            46,
            466,
            46,
            466,
            46,
            466,
            46,
            466,
            46,
            466,
            46,
            466,
            46,
            466,
            46,
            466,
            46,
            466,
            46,
            466,
            46,
            466,
            46,
            466,
            46,
            466,
            46,
            466,
            46,
            466,
            46,
            466,
            46,
            466,
            46,
            466,
            46,
            466,
            46,
            466,
            46,
            466,
            46,
            466,
            46,
            466,
            46,
            466,
            46,
            466,
            46,
            466,
            46,
            466,
            46,
            466,
            46,
            466,
            46,
            466,
            46,
            466,
            46,
            466,
            46,
            466,
            46,
            466,
            46,
            466,
            46,
            466,
            46,
            466,
            46,
            466,
            46,
            466,
            46,
            466,
            46,
            466,
            46,
            466,
            46,
            466,
            46,
            466,
            46,
            466,
            46,
            466,
            46,
            466,
            46,
            466,
            46,
            466,
            46,
            466,
            46,
            466,
            46,
            466,
            46,
            466,
            46,
            466,
            46,
            466,
            46,
            466,
            46,
            466,
            46,
            466,
            46,
            466,
            46,
            466,
            46,
            466,
            46,
            466,
            46,
            466,
            46,
            466,
            46,
            466,
            46,
            466,
            46,
            466,
            46,
            466,
            46,
            466,
            46,
            466,
            46,
            466,
            46,
            466,
            46,
            466,
            46,
            466,
            46,
            466,
            46,
            466,
            46,
            466,
            46,
            466,
            46,
            466,
            46,
            466,
            46,
            466,
            46,
            466,
            46,
            466,
            46,
            466,
            46,
            466,
            46,
            466,
            46,
            466,
            46,
            466,
            46,
            466,
            46,
            466,
            46,
            466,
            46,
            466,
            46,
            466,
            46,
            466,
            46,
            466,
            46,
            466,
            46,
            466,
            46,
            466,
            46,
            466,
            46,
            466,
            46,
            466,
            46,
            466,
            46,
            466,
            46,
            466,
            46,
            466,
            46,
            466,
            46,
            466,
            46,
            466,
            46,
            466,
            46,
            466,
            46,
            466,
            46,
            466,
            46,
            466,
            46,
            466,
            46,
            466,
            46,
            466,
            46,
            466,
            46,
            466,
            46,
            466,
            46,
            466,
            46,
            466,
            46,
            466,
            46,
            466,
            46,
            466,
            46,
            466,
            46,
            466,
            46,
            466,
            46,
            466,
            46,
            466,
            46,
            466,
            46,
            466,
            46,
            466,
            46,
            466,
            46,
            466,
            46,
            466,
            46,
            466,
            46,
            466,
            46,
            466,
            46,
            466,
            46,
            466,
            46,
            466,
            46,
            466,
            46,
            466,
            46,
            466,
            46,
            466,
            46,
            466,
            46,
            466,
            46,
            466,
            46,
            466,
            46,
            466,
            46,
            466,
            33,
            9,
            4,
            466,
            33,
            11,
            2,
            466,
            33,
            479,
            33,
            479,
            33,
            479,
            33,
            479,
            33,
            479,
            33,
            479,
            33,
            479,
            33,
            479,
            33,
            479,
            34,
            478,
            34,
            478,
            34,
            478,
            34,
            478,
            34,
            478,
            34,
            478,
            34,
            478,
            34,
            478,
            34,
            479,
            33,
            480,
            32,
            481,
            32,
            481,
            31,
            481,
            31,
            482,
            30,
            483,
            29,
            484,
            28,
            485,
            27,
            487,
            25,
            488,
            24,
            489,
            23,
            489,
            23,
            490,
            22,
            492,
            20,
            493,
            19,
            494,
            18,
            496,
            16,
            497,
            15,
            499,
            13,
            500,
            11,
            502,
            10,
            503,
            8,
            505,
            6,
            72993
          ],
          "format": "uncompressed_rle"
        },
        "method": "geometric_taxonomy",
        "crop_file": "C:\\Users\\netta\\OneDrive\\Documents\\Coding Projects\\3D renderer and segmenter\\output\\segmenter\\HAD95_3579_1\\part_crops\\neck\\HAD95_3579_1_phi_180_theta_140__neck.png"
      },
      {
        "part_name": "shoulder",
        "confidence": 0.6756,
        "low_confidence": false,
        "quality_score": 0.8378,
        "bbox_xywh": [
          143,
          237,
          196,
          49
        ],
        "mask_area_px": 9037,
        "mask_rle": {
          "size": [
            512,
            512
          ],
          "counts": [
            73499,
            3,
            504,
            8,
            500,
            12,
            497,
            15,
            493,
            19,
            490,
            22,
            488,
            24,
            485,
            27,
            482,
            30,
            479,
            33,
            477,
            35,
            473,
            39,
            470,
            42,
            467,
            45,
            464,
            48,
            463,
            49,
            463,
            49,
            463,
            49,
            463,
            49,
            463,
            49,
            463,
            49,
            463,
            49,
            463,
            49,
            463,
            49,
            463,
            49,
            463,
            49,
            463,
            49,
            463,
            49,
            463,
            49,
            463,
            49,
            463,
            49,
            463,
            49,
            463,
            49,
            463,
            49,
            463,
            49,
            463,
            49,
            463,
            49,
            463,
            49,
            463,
            49,
            463,
            49,
            463,
            49,
            463,
            49,
            463,
            49,
            463,
            49,
            463,
            49,
            463,
            49,
            463,
            49,
            463,
            49,
            463,
            49,
            463,
            49,
            463,
            49,
            463,
            49,
            463,
            49,
            463,
            49,
            463,
            49,
            463,
            49,
            463,
            49,
            463,
            49,
            463,
            49,
            463,
            49,
            463,
            49,
            463,
            49,
            463,
            49,
            463,
            49,
            463,
            49,
            463,
            49,
            463,
            49,
            463,
            49,
            463,
            49,
            463,
            49,
            463,
            49,
            463,
            49,
            463,
            49,
            463,
            49,
            463,
            49,
            463,
            49,
            463,
            49,
            463,
            49,
            463,
            49,
            463,
            49,
            463,
            49,
            463,
            49,
            463,
            49,
            463,
            49,
            463,
            49,
            463,
            49,
            463,
            49,
            463,
            49,
            463,
            49,
            463,
            49,
            463,
            49,
            463,
            49,
            463,
            49,
            463,
            49,
            463,
            49,
            463,
            49,
            463,
            49,
            463,
            49,
            463,
            49,
            463,
            49,
            463,
            49,
            463,
            49,
            463,
            49,
            463,
            49,
            463,
            49,
            463,
            49,
            463,
            49,
            463,
            49,
            463,
            49,
            463,
            49,
            463,
            49,
            463,
            49,
            463,
            49,
            463,
            49,
            463,
            49,
            463,
            49,
            463,
            49,
            463,
            49,
            463,
            49,
            463,
            49,
            463,
            49,
            463,
            49,
            463,
            49,
            463,
            49,
            463,
            49,
            463,
            49,
            463,
            49,
            463,
            49,
            463,
            49,
            463,
            49,
            463,
            49,
            463,
            49,
            463,
            49,
            463,
            49,
            463,
            49,
            463,
            49,
            463,
            49,
            463,
            49,
            463,
            49,
            463,
            49,
            463,
            49,
            463,
            49,
            463,
            49,
            463,
            49,
            463,
            49,
            463,
            49,
            463,
            49,
            463,
            49,
            463,
            49,
            463,
            49,
            463,
            49,
            463,
            49,
            463,
            49,
            463,
            49,
            463,
            49,
            463,
            49,
            463,
            49,
            463,
            49,
            463,
            49,
            463,
            49,
            463,
            49,
            463,
            49,
            463,
            49,
            463,
            49,
            463,
            49,
            463,
            49,
            463,
            49,
            463,
            49,
            463,
            49,
            463,
            49,
            463,
            49,
            463,
            49,
            463,
            49,
            463,
            49,
            463,
            49,
            463,
            49,
            463,
            49,
            463,
            49,
            463,
            49,
            463,
            49,
            463,
            49,
            463,
            49,
            463,
            49,
            463,
            49,
            463,
            49,
            464,
            48,
            467,
            45,
            470,
            42,
            475,
            37,
            478,
            34,
            482,
            30,
            487,
            25,
            493,
            19,
            499,
            13,
            504,
            8,
            508,
            4,
            88802
          ],
          "format": "uncompressed_rle"
        },
        "method": "geometric_taxonomy",
        "crop_file": "C:\\Users\\netta\\OneDrive\\Documents\\Coding Projects\\3D renderer and segmenter\\output\\segmenter\\HAD95_3579_1\\part_crops\\shoulder\\HAD95_3579_1_phi_180_theta_140__shoulder.png"
      },
      {
        "part_name": "body",
        "confidence": 0.85,
        "low_confidence": false,
        "quality_score": 0.925,
        "bbox_xywh": [
          131,
          257,
          224,
          144
        ],
        "mask_area_px": 28847,
        "mask_rle": {
          "size": [
            512,
            512
          ],
          "counts": [
            67426,
            6,
            497,
            23,
            11,
            13,
            460,
            59,
            450,
            64,
            435,
            77,
            432,
            80,
            424,
            88,
            413,
            99,
            410,
            102,
            406,
            106,
            401,
            111,
            397,
            115,
            394,
            118,
            389,
            123,
            385,
            127,
            382,
            130,
            378,
            134,
            375,
            137,
            373,
            139,
            370,
            142,
            368,
            144,
            368,
            144,
            368,
            144,
            368,
            144,
            368,
            144,
            368,
            144,
            368,
            144,
            368,
            144,
            368,
            144,
            368,
            144,
            368,
            144,
            368,
            144,
            368,
            144,
            368,
            144,
            368,
            144,
            368,
            144,
            368,
            144,
            368,
            144,
            368,
            144,
            368,
            144,
            368,
            144,
            368,
            144,
            368,
            144,
            368,
            144,
            368,
            144,
            368,
            144,
            368,
            144,
            368,
            144,
            368,
            144,
            368,
            144,
            368,
            144,
            368,
            144,
            368,
            144,
            368,
            144,
            368,
            144,
            368,
            144,
            368,
            144,
            368,
            144,
            368,
            144,
            368,
            144,
            368,
            144,
            368,
            144,
            368,
            144,
            368,
            144,
            368,
            144,
            368,
            144,
            368,
            144,
            368,
            144,
            368,
            144,
            368,
            144,
            368,
            144,
            368,
            144,
            368,
            144,
            368,
            144,
            368,
            144,
            368,
            144,
            368,
            144,
            368,
            144,
            368,
            144,
            368,
            144,
            368,
            144,
            368,
            144,
            368,
            144,
            368,
            144,
            368,
            144,
            368,
            144,
            368,
            68,
            10,
            66,
            368,
            68,
            10,
            66,
            368,
            68,
            11,
            65,
            368,
            68,
            11,
            65,
            368,
            68,
            11,
            65,
            368,
            68,
            11,
            65,
            368,
            68,
            11,
            65,
            368,
            68,
            12,
            64,
            368,
            68,
            12,
            64,
            368,
            69,
            11,
            64,
            368,
            69,
            11,
            64,
            368,
            69,
            11,
            64,
            368,
            69,
            12,
            63,
            368,
            69,
            13,
            62,
            368,
            70,
            12,
            62,
            368,
            70,
            12,
            62,
            368,
            70,
            12,
            62,
            368,
            70,
            12,
            62,
            368,
            70,
            12,
            62,
            368,
            70,
            12,
            62,
            368,
            70,
            12,
            62,
            368,
            70,
            12,
            62,
            368,
            70,
            12,
            62,
            368,
            70,
            12,
            62,
            368,
            70,
            12,
            62,
            368,
            70,
            12,
            62,
            368,
            70,
            12,
            62,
            368,
            70,
            12,
            62,
            368,
            70,
            12,
            62,
            368,
            70,
            12,
            62,
            368,
            70,
            12,
            62,
            368,
            70,
            12,
            62,
            368,
            70,
            12,
            62,
            368,
            70,
            12,
            62,
            368,
            70,
            12,
            62,
            368,
            70,
            12,
            62,
            368,
            70,
            12,
            62,
            368,
            70,
            12,
            62,
            368,
            70,
            12,
            62,
            368,
            70,
            12,
            62,
            368,
            69,
            12,
            63,
            368,
            69,
            12,
            63,
            368,
            69,
            12,
            63,
            368,
            69,
            12,
            63,
            368,
            69,
            12,
            63,
            368,
            69,
            12,
            63,
            368,
            69,
            12,
            63,
            368,
            68,
            13,
            63,
            368,
            68,
            13,
            63,
            368,
            68,
            12,
            64,
            368,
            68,
            11,
            65,
            368,
            68,
            11,
            65,
            368,
            68,
            11,
            65,
            368,
            68,
            11,
            65,
            368,
            68,
            9,
            67,
            368,
            68,
            9,
            67,
            368,
            68,
            9,
            67,
            368,
            144,
            368,
            144,
            368,
            144,
            368,
            144,
            368,
            144,
            368,
            144,
            368,
            144,
            368,
            144,
            368,
            144,
            368,
            144,
            368,
            144,
            368,
            144,
            368,
            144,
            368,
            144,
            368,
            144,
            368,
            144,
            368,
            144,
            368,
            144,
            368,
            144,
            368,
            144,
            368,
            144,
            368,
            144,
            368,
            144,
            368,
            144,
            368,
            144,
            368,
            144,
            368,
            144,
            368,
            144,
            368,
            144,
            368,
            144,
            368,
            144,
            368,
            144,
            368,
            144,
            368,
            143,
            369,
            142,
            370,
            142,
            370,
            141,
            371,
            140,
            372,
            140,
            372,
            139,
            373,
            139,
            373,
            139,
            373,
            138,
            374,
            137,
            375,
            137,
            375,
            136,
            376,
            136,
            376,
            135,
            377,
            133,
            379,
            132,
            380,
            132,
            380,
            131,
            381,
            131,
            381,
            130,
            382,
            130,
            382,
            130,
            382,
            130,
            382,
            130,
            382,
            129,
            383,
            128,
            388,
            123,
            395,
            116,
            402,
            109,
            408,
            104,
            412,
            99,
            421,
            90,
            425,
            86,
            429,
            82,
            432,
            80,
            437,
            75,
            443,
            68,
            449,
            63,
            454,
            57,
            459,
            52,
            466,
            45,
            471,
            41,
            475,
            36,
            481,
            30,
            487,
            24,
            497,
            14,
            503,
            8,
            80527
          ],
          "format": "uncompressed_rle"
        },
        "method": "geometric_taxonomy",
        "crop_file": "C:\\Users\\netta\\OneDrive\\Documents\\Coding Projects\\3D renderer and segmenter\\output\\segmenter\\HAD95_3579_1\\part_crops\\body\\HAD95_3579_1_phi_180_theta_140__body.png"
      },
      {
        "part_name": "base",
        "confidence": 0.5903,
        "low_confidence": false,
        "quality_score": 0.7644,
        "bbox_xywh": [
          133,
          393,
          186,
          52
        ],
        "mask_area_px": 5617,
        "mask_rle": {
          "size": [
            512,
            512
          ],
          "counts": [
            68489,
            6,
            506,
            8,
            504,
            10,
            502,
            11,
            501,
            11,
            501,
            12,
            500,
            13,
            499,
            13,
            499,
            14,
            498,
            15,
            497,
            15,
            497,
            16,
            496,
            16,
            496,
            17,
            495,
            17,
            495,
            18,
            494,
            19,
            493,
            20,
            492,
            21,
            491,
            21,
            491,
            22,
            490,
            23,
            489,
            24,
            488,
            24,
            488,
            25,
            487,
            25,
            487,
            25,
            487,
            26,
            486,
            26,
            486,
            26,
            486,
            27,
            485,
            27,
            485,
            28,
            484,
            28,
            484,
            29,
            483,
            30,
            482,
            31,
            481,
            32,
            480,
            33,
            479,
            33,
            479,
            34,
            478,
            35,
            477,
            35,
            477,
            35,
            477,
            36,
            476,
            36,
            476,
            37,
            475,
            38,
            474,
            38,
            474,
            39,
            473,
            39,
            473,
            40,
            472,
            40,
            472,
            41,
            471,
            41,
            471,
            42,
            470,
            42,
            470,
            43,
            469,
            43,
            469,
            44,
            468,
            44,
            468,
            45,
            467,
            45,
            467,
            46,
            466,
            46,
            466,
            47,
            465,
            47,
            465,
            48,
            464,
            48,
            464,
            49,
            463,
            49,
            463,
            49,
            463,
            50,
            462,
            50,
            462,
            51,
            461,
            51,
            461,
            52,
            460,
            52,
            460,
            52,
            460,
            52,
            460,
            52,
            460,
            52,
            460,
            52,
            460,
            52,
            460,
            52,
            460,
            52,
            460,
            52,
            460,
            51,
            461,
            51,
            461,
            51,
            461,
            50,
            462,
            50,
            462,
            50,
            462,
            49,
            463,
            49,
            463,
            48,
            464,
            48,
            464,
            47,
            465,
            47,
            465,
            46,
            466,
            46,
            466,
            45,
            467,
            44,
            468,
            44,
            468,
            44,
            468,
            44,
            468,
            43,
            469,
            43,
            469,
            42,
            470,
            41,
            471,
            41,
            471,
            40,
            472,
            40,
            472,
            39,
            473,
            39,
            473,
            38,
            474,
            38,
            474,
            37,
            475,
            36,
            476,
            35,
            477,
            35,
            477,
            35,
            477,
            34,
            478,
            34,
            478,
            33,
            479,
            33,
            479,
            32,
            480,
            32,
            480,
            31,
            481,
            31,
            481,
            30,
            482,
            30,
            482,
            29,
            483,
            28,
            484,
            27,
            485,
            26,
            486,
            25,
            487,
            24,
            488,
            24,
            488,
            24,
            488,
            24,
            488,
            24,
            488,
            24,
            488,
            23,
            489,
            23,
            489,
            23,
            489,
            22,
            490,
            22,
            490,
            22,
            490,
            21,
            491,
            21,
            491,
            20,
            492,
            19,
            493,
            18,
            494,
            17,
            495,
            17,
            495,
            16,
            496,
            16,
            496,
            15,
            497,
            15,
            497,
            15,
            497,
            14,
            498,
            14,
            498,
            14,
            498,
            13,
            499,
            13,
            499,
            12,
            500,
            12,
            500,
            11,
            501,
            11,
            501,
            10,
            502,
            9,
            503,
            9,
            503,
            8,
            504,
            7,
            505,
            6,
            506,
            6,
            506,
            5,
            507,
            4,
            508,
            4,
            508,
            3,
            509,
            3,
            509,
            3,
            509,
            2,
            510,
            1,
            511,
            1,
            98934
          ],
          "format": "uncompressed_rle"
        },
        "method": "geometric_taxonomy",
        "crop_file": "C:\\Users\\netta\\OneDrive\\Documents\\Coding Projects\\3D renderer and segmenter\\output\\segmenter\\HAD95_3579_1\\part_crops\\base\\HAD95_3579_1_phi_180_theta_140__base.png"
      },
      {
        "part_name": "foot",
        "confidence": 0.5188,
        "low_confidence": true,
        "quality_score": 0.5914,
        "bbox_xywh": [
          148,
          410,
          139,
          35
        ],
        "mask_area_px": 2754,
        "mask_rle": {
          "size": [
            512,
            512
          ],
          "counts": [
            76186,
            1,
            511,
            2,
            510,
            3,
            509,
            4,
            508,
            4,
            508,
            5,
            507,
            6,
            506,
            7,
            505,
            7,
            505,
            8,
            504,
            8,
            504,
            8,
            504,
            9,
            503,
            9,
            503,
            9,
            503,
            10,
            502,
            10,
            502,
            11,
            501,
            11,
            501,
            12,
            500,
            13,
            499,
            14,
            498,
            15,
            497,
            16,
            496,
            16,
            496,
            17,
            495,
            18,
            494,
            18,
            494,
            18,
            494,
            19,
            493,
            19,
            493,
            20,
            492,
            21,
            491,
            21,
            491,
            22,
            490,
            22,
            490,
            23,
            489,
            23,
            489,
            24,
            488,
            24,
            488,
            25,
            487,
            25,
            487,
            26,
            486,
            26,
            486,
            27,
            485,
            27,
            485,
            28,
            484,
            28,
            484,
            29,
            483,
            29,
            483,
            30,
            482,
            30,
            482,
            31,
            481,
            31,
            481,
            32,
            480,
            32,
            480,
            32,
            480,
            33,
            479,
            33,
            479,
            34,
            478,
            34,
            478,
            35,
            477,
            35,
            477,
            35,
            477,
            35,
            477,
            35,
            477,
            35,
            477,
            35,
            477,
            35,
            477,
            35,
            477,
            35,
            477,
            35,
            477,
            34,
            478,
            34,
            478,
            34,
            478,
            33,
            479,
            33,
            479,
            33,
            479,
            32,
            480,
            32,
            480,
            31,
            481,
            31,
            481,
            30,
            482,
            30,
            482,
            29,
            483,
            29,
            483,
            28,
            484,
            27,
            485,
            27,
            485,
            27,
            485,
            27,
            485,
            26,
            486,
            26,
            486,
            25,
            487,
            24,
            488,
            24,
            488,
            23,
            489,
            23,
            489,
            22,
            490,
            22,
            490,
            21,
            491,
            21,
            491,
            20,
            492,
            19,
            493,
            18,
            494,
            18,
            494,
            18,
            494,
            17,
            495,
            17,
            495,
            16,
            496,
            16,
            496,
            15,
            497,
            15,
            497,
            14,
            498,
            14,
            498,
            13,
            499,
            13,
            499,
            12,
            500,
            11,
            501,
            10,
            502,
            9,
            503,
            8,
            504,
            7,
            505,
            7,
            505,
            7,
            505,
            7,
            505,
            7,
            505,
            7,
            505,
            6,
            506,
            6,
            506,
            6,
            506,
            5,
            507,
            5,
            507,
            5,
            507,
            4,
            508,
            4,
            508,
            3,
            509,
            2,
            510,
            1,
            115301
          ],
          "format": "uncompressed_rle"
        },
        "method": "geometric_taxonomy",
        "crop_file": "C:\\Users\\netta\\OneDrive\\Documents\\Coding Projects\\3D renderer and segmenter\\output\\segmenter\\HAD95_3579_1\\part_crops\\foot\\HAD95_3579_1_phi_180_theta_140__foot.png"
      },
      {
        "part_name": "handle",
        "confidence": 0.85,
        "low_confidence": false,
        "quality_score": 0.925,
        "bbox_xywh": [
          131,
          214,
          239,
          159
        ],
        "mask_area_px": 18924,
        "mask_rle": {
          "size": [
            512,
            512
          ],
          "counts": [
            67426,
            6,
            497,
            23,
            484,
            33,
            476,
            36,
            463,
            49,
            460,
            52,
            452,
            60,
            441,
            71,
            438,
            74,
            434,
            78,
            429,
            83,
            425,
            87,
            422,
            90,
            417,
            95,
            413,
            99,
            410,
            102,
            406,
            106,
            403,
            109,
            401,
            111,
            398,
            114,
            395,
            117,
            392,
            120,
            390,
            122,
            386,
            126,
            383,
            129,
            380,
            132,
            377,
            135,
            373,
            139,
            371,
            141,
            368,
            144,
            366,
            146,
            363,
            149,
            361,
            151,
            359,
            153,
            358,
            154,
            356,
            156,
            353,
            159,
            353,
            159,
            353,
            159,
            353,
            159,
            353,
            159,
            353,
            159,
            353,
            159,
            353,
            159,
            353,
            159,
            353,
            159,
            353,
            159,
            353,
            159,
            353,
            159,
            353,
            159,
            353,
            159,
            353,
            159,
            353,
            159,
            353,
            159,
            353,
            159,
            353,
            159,
            353,
            159,
            353,
            159,
            353,
            159,
            353,
            159,
            353,
            159,
            353,
            159,
            353,
            159,
            353,
            159,
            353,
            159,
            353,
            159,
            353,
            159,
            353,
            159,
            353,
            159,
            353,
            159,
            353,
            159,
            353,
            159,
            353,
            159,
            353,
            159,
            353,
            159,
            353,
            159,
            353,
            159,
            353,
            159,
            41825,
            159,
            353,
            159,
            353,
            159,
            353,
            159,
            353,
            159,
            353,
            159,
            353,
            159,
            353,
            159,
            353,
            159,
            353,
            159,
            353,
            159,
            353,
            159,
            353,
            159,
            353,
            159,
            353,
            159,
            353,
            159,
            353,
            159,
            353,
            159,
            353,
            159,
            353,
            159,
            353,
            159,
            353,
            159,
            353,
            159,
            353,
            159,
            353,
            159,
            353,
            159,
            353,
            159,
            353,
            159,
            353,
            159,
            353,
            159,
            353,
            159,
            353,
            159,
            353,
            159,
            353,
            159,
            353,
            159,
            353,
            159,
            353,
            10,
            9,
            140,
            353,
            10,
            11,
            138,
            353,
            10,
            14,
            135,
            353,
            10,
            17,
            132,
            353,
            10,
            20,
            129,
            353,
            10,
            25,
            124,
            353,
            10,
            28,
            121,
            353,
            10,
            32,
            117,
            353,
            10,
            37,
            112,
            353,
            10,
            43,
            106,
            353,
            10,
            49,
            100,
            353,
            11,
            53,
            95,
            353,
            11,
            57,
            91,
            353,
            11,
            65,
            83,
            353,
            11,
            68,
            80,
            353,
            11,
            71,
            77,
            353,
            11,
            73,
            75,
            353,
            11,
            78,
            70,
            353,
            11,
            84,
            64,
            353,
            11,
            89,
            59,
            353,
            11,
            94,
            54,
            353,
            11,
            98,
            50,
            353,
            12,
            103,
            44,
            353,
            12,
            107,
            40,
            353,
            12,
            111,
            36,
            353,
            12,
            116,
            30,
            354,
            12,
            121,
            24,
            355,
            12,
            130,
            14,
            356,
            12,
            135,
            8,
            357,
            12,
            500,
            12,
            500,
            12,
            500,
            12,
            500,
            12,
            500,
            12,
            500,
            12,
            500,
            12,
            500,
            12,
            500,
            12,
            500,
            12,
            500,
            11,
            502,
            10,
            503,
            8,
            505,
            6,
            72993
          ],
          "format": "uncompressed_rle"
        },
        "method": "geometric_taxonomy",
        "crop_file": "C:\\Users\\netta\\OneDrive\\Documents\\Coding Projects\\3D renderer and segmenter\\output\\segmenter\\HAD95_3579_1\\part_crops\\handle\\HAD95_3579_1_phi_180_theta_140__handle.png"
      },
      {
        "part_name": "spout",
        "confidence": 0.6702,
        "low_confidence": false,
        "quality_score": 0.8351,
        "bbox_xywh": [
          144,
          171,
          226,
          86
        ],
        "mask_area_px": 8819,
        "mask_rle": {
          "size": [
            512,
            512
          ],
          "counts": [
            73921,
            5,
            507,
            7,
            504,
            10,
            501,
            12,
            499,
            13,
            498,
            14,
            498,
            14,
            497,
            15,
            53,
            1,
            442,
            16,
            50,
            4,
            442,
            16,
            48,
            6,
            441,
            18,
            43,
            10,
            440,
            19,
            40,
            13,
            440,
            19,
            37,
            16,
            439,
            20,
            34,
            19,
            439,
            20,
            30,
            23,
            438,
            21,
            28,
            25,
            437,
            22,
            25,
            28,
            437,
            22,
            23,
            30,
            436,
            24,
            19,
            33,
            435,
            25,
            17,
            35,
            435,
            25,
            15,
            37,
            434,
            26,
            14,
            38,
            434,
            26,
            12,
            40,
            433,
            27,
            9,
            43,
            433,
            79,
            432,
            80,
            432,
            80,
            431,
            81,
            431,
            81,
            430,
            82,
            430,
            82,
            429,
            83,
            429,
            83,
            428,
            84,
            427,
            85,
            427,
            85,
            427,
            85,
            426,
            86,
            426,
            86,
            426,
            86,
            426,
            86,
            426,
            86,
            426,
            86,
            426,
            86,
            426,
            86,
            426,
            86,
            426,
            86,
            426,
            86,
            426,
            86,
            426,
            86,
            426,
            86,
            426,
            86,
            426,
            86,
            426,
            86,
            426,
            86,
            426,
            86,
            426,
            86,
            426,
            86,
            426,
            86,
            426,
            86,
            426,
            86,
            426,
            86,
            426,
            86,
            426,
            86,
            426,
            86,
            41898,
            86,
            426,
            86,
            426,
            86,
            426,
            86,
            426,
            86,
            426,
            86,
            426,
            86,
            426,
            86,
            426,
            86,
            426,
            86,
            426,
            86,
            426,
            86,
            426,
            86,
            426,
            86,
            426,
            86,
            426,
            86,
            426,
            86,
            426,
            86,
            426,
            86,
            426,
            86,
            426,
            86,
            426,
            86,
            426,
            86,
            426,
            86,
            426,
            86,
            427,
            85,
            427,
            85,
            428,
            84,
            428,
            84,
            429,
            83,
            429,
            83,
            430,
            82,
            430,
            82,
            431,
            81,
            432,
            80,
            432,
            80,
            433,
            46,
            9,
            24,
            433,
            46,
            11,
            22,
            434,
            45,
            14,
            19,
            434,
            45,
            17,
            16,
            435,
            44,
            20,
            13,
            436,
            43,
            25,
            8,
            436,
            43,
            28,
            5,
            437,
            42,
            32,
            1,
            438,
            41,
            471,
            41,
            472,
            40,
            473,
            40,
            472,
            40,
            473,
            39,
            474,
            38,
            475,
            37,
            476,
            36,
            476,
            36,
            477,
            35,
            478,
            34,
            479,
            33,
            480,
            32,
            481,
            32,
            481,
            31,
            481,
            31,
            482,
            30,
            483,
            29,
            484,
            28,
            485,
            27,
            487,
            25,
            488,
            24,
            489,
            23,
            489,
            23,
            490,
            22,
            492,
            20,
            493,
            19,
            494,
            18,
            496,
            16,
            497,
            15,
            499,
            13,
            500,
            11,
            502,
            10,
            503,
            8,
            505,
            6,
            72993
          ],
          "format": "uncompressed_rle"
        },
        "method": "geometric_taxonomy",
        "crop_file": "C:\\Users\\netta\\OneDrive\\Documents\\Coding Projects\\3D renderer and segmenter\\output\\segmenter\\HAD95_3579_1\\part_crops\\spout\\HAD95_3579_1_phi_180_theta_140__spout.png"
      }
    ]
  }
}