{
  "schema_version": "0.1",
  "artifact_id": "HAD95_3579_1",
  "artifact_class": "pottery",
  "image": {
    "image_filename": "HAD95_3579_1__phi_320__theta_100.png",
    "image_path": "C:\\Users\\netta\\OneDrive\\Documents\\Coding Projects\\3D renderer and segmenter\\output\\images\\unclassified\\HAD95_3579_1\\HAD95_3579_1__phi_320__theta_100.png",
    "angle_metadata": {
      "phi": 320,
      "theta": 100,
      "elevation": null
    },
    "width": 512,
    "height": 512,
    "annotated_file": "C:\\Users\\netta\\OneDrive\\Documents\\Coding Projects\\3D renderer and segmenter\\output\\segmenter\\HAD95_3579_1\\annotated\\HAD95_3579_1_phi_320_theta_100__annotated.png",
    "clean_visual_file": "C:\\Users\\netta\\OneDrive\\Documents\\Coding Projects\\3D renderer and segmenter\\output\\segmenter\\HAD95_3579_1\\clean_visual\\HAD95_3579_1_phi_320_theta_100__clean.png",
    "parts": [
      {
        "part_name": "rim",
        "confidence": 0.5416,
        "low_confidence": true,
        "quality_score": 0.6467,
        "bbox_xywh": [
          193,
          88,
          127,
          41
        ],
        "mask_area_px": 3291,
        "mask_rle": {
          "size": [
            512,
            512
          ],
          "counts": [
            98944,
            1,
            511,
            1,
            511,
            1,
            502,
            10,
            500,
            12,
            496,
            16,
            493,
            19,
            491,
            21,
            489,
            23,
            487,
            25,
            485,
            27,
            483,
            29,
            481,
            31,
            479,
            33,
            477,
            35,
            475,
            37,
            473,
            39,
            473,
            39,
            472,
            40,
            471,
            41,
            471,
            41,
            471,
            41,
            471,
            41,
            471,
            41,
            471,
            41,
            471,
            41,
            471,
            41,
            471,
            41,
            472,
            40,
            472,
            40,
            472,
            40,
            472,
            40,
            472,
            40,
            472,
            40,
            472,
            40,
            472,
            40,
            472,
            40,
            472,
            40,
            472,
            40,
            473,
            39,
            473,
            39,
            473,
            39,
            473,
            39,
            474,
            38,
            474,
            38,
            474,
            38,
            474,
            38,
            474,
            38,
            475,
            37,
            475,
            37,
            475,
            37,
            476,
            36,
            476,
            36,
            476,
            36,
            477,
            35,
            477,
            35,
            477,
            35,
            477,
            35,
            478,
            34,
            478,
            34,
            478,
            34,
            479,
            33,
            479,
            33,
            479,
            33,
            480,
            32,
            480,
            32,
            480,
            32,
            481,
            31,
            481,
            31,
            482,
            30,
            482,
            30,
            482,
            30,
            483,
            29,
            483,
            29,
            483,
            29,
            484,
            28,
            484,
            28,
            485,
            27,
            485,
            27,
            486,
            26,
            486,
            26,
            486,
            26,
            487,
            25,
            487,
            25,
            488,
            24,
            488,
            24,
            489,
            23,
            489,
            23,
            490,
            22,
            490,
            22,
            491,
            21,
            491,
            21,
            492,
            20,
            492,
            20,
            493,
            19,
            493,
            19,
            494,
            18,
            494,
            18,
            495,
            17,
            495,
            17,
            496,
            16,
            496,
            16,
            497,
            15,
            497,
            15,
            498,
            14,
            498,
            14,
            499,
            13,
            500,
            12,
            500,
            12,
            501,
            11,
            501,
            11,
            502,
            10,
            503,
            9,
            503,
            9,
            504,
            8,
            504,
            8,
            505,
            7,
            506,
            6,
            506,
            6,
            507,
            5,
            507,
            5,
            508,
            4,
            509,
            3,
            509,
            3,
            510,
            2,
            511,
            1,
            511,
            1,
            98687
          ],
          "format": "uncompressed_rle"
        },
        "method": "geometric_taxonomy",
        "crop_file": "C:\\Users\\netta\\OneDrive\\Documents\\Coding Projects\\3D renderer and segmenter\\output\\segmenter\\HAD95_3579_1\\part_crops\\rim\\HAD95_3579_1_phi_320_theta_100__rim.png"
      },
      {
        "part_name": "neck",
        "confidence": 0.6629,
        "low_confidence": false,
        "quality_score": 0.8315,
        "bbox_xywh": [
          161,
          129,
          170,
          55
        ],
        "mask_area_px": 7648,
        "mask_rle": {
          "size": [
            512,
            512
          ],
          "counts": [
            82615,
            1,
            510,
            2,
            509,
            3,
            509,
            3,
            508,
            4,
            508,
            4,
            507,
            5,
            506,
            6,
            505,
            7,
            505,
            7,
            504,
            8,
            503,
            9,
            502,
            10,
            502,
            10,
            501,
            11,
            500,
            12,
            499,
            13,
            497,
            15,
            494,
            18,
            490,
            22,
            485,
            27,
            481,
            31,
            479,
            33,
            475,
            37,
            472,
            40,
            470,
            42,
            467,
            45,
            465,
            47,
            463,
            49,
            461,
            51,
            460,
            52,
            458,
            54,
            457,
            55,
            457,
            55,
            457,
            55,
            457,
            55,
            457,
            55,
            457,
            55,
            457,
            55,
            457,
            55,
            457,
            55,
            457,
            55,
            457,
            55,
            457,
            55,
            457,
            55,
            457,
            55,
            457,
            55,
            457,
            55,
            457,
            55,
            457,
            55,
            457,
            55,
            457,
            55,
            457,
            55,
            457,
            55,
            457,
            55,
            457,
            55,
            457,
            55,
            457,
            55,
            457,
            55,
            457,
            55,
            457,
            55,
            457,
            55,
            457,
            55,
            457,
            55,
            457,
            55,
            457,
            55,
            457,
            55,
            457,
            55,
            457,
            55,
            457,
            55,
            457,
            55,
            457,
            55,
            457,
            55,
            457,
            55,
            457,
            55,
            457,
            55,
            457,
            55,
            457,
            55,
            457,
            55,
            457,
            55,
            457,
            55,
            457,
            55,
            457,
            55,
            457,
            55,
            457,
            55,
            457,
            55,
            457,
            55,
            457,
            55,
            457,
            55,
            457,
            55,
            457,
            55,
            457,
            55,
            457,
            55,
            457,
            55,
            457,
            55,
            457,
            55,
            457,
            55,
            457,
            55,
            457,
            55,
            457,
            55,
            457,
            55,
            457,
            55,
            457,
            55,
            457,
            55,
            457,
            55,
            457,
            55,
            457,
            55,
            457,
            55,
            457,
            55,
            457,
            55,
            457,
            55,
            457,
            55,
            457,
            55,
            457,
            55,
            457,
            55,
            457,
            55,
            457,
            55,
            457,
            55,
            457,
            55,
            457,
            55,
            457,
            55,
            457,
            55,
            457,
            55,
            457,
            55,
            457,
            55,
            457,
            55,
            457,
            55,
            457,
            55,
            457,
            55,
            457,
            55,
            457,
            55,
            457,
            55,
            457,
            55,
            457,
            55,
            457,
            55,
            457,
            55,
            457,
            55,
            457,
            55,
            457,
            55,
            457,
            55,
            457,
            55,
            457,
            55,
            457,
            55,
            457,
            55,
            457,
            55,
            457,
            55,
            457,
            55,
            457,
            55,
            457,
            53,
            459,
            41,
            471,
            39,
            473,
            38,
            474,
            37,
            475,
            36,
            476,
            35,
            477,
            33,
            479,
            32,
            480,
            30,
            482,
            29,
            483,
            27,
            486,
            25,
            487,
            24,
            489,
            22,
            490,
            20,
            493,
            17,
            496,
            14,
            498,
            13,
            500,
            11,
            502,
            8,
            504,
            6,
            93043
          ],
          "format": "uncompressed_rle"
        },
        "method": "geometric_taxonomy",
        "crop_file": "C:\\Users\\netta\\OneDrive\\Documents\\Coding Projects\\3D renderer and segmenter\\output\\segmenter\\HAD95_3579_1\\part_crops\\neck\\HAD95_3579_1_phi_320_theta_100__neck.png"
      },
      {
        "part_name": "shoulder",
        "confidence": 0.7076,
        "low_confidence": false,
        "quality_score": 0.8538,
        "bbox_xywh": [
          143,
          184,
          172,
          58
        ],
        "mask_area_px": 9253,
        "mask_rle": {
          "size": [
            512,
            512
          ],
          "counts": [
            73426,
            7,
            505,
            11,
            501,
            14,
            492,
            22,
            488,
            26,
            485,
            28,
            481,
            33,
            478,
            35,
            475,
            39,
            472,
            40,
            470,
            44,
            467,
            46,
            465,
            48,
            463,
            50,
            461,
            52,
            458,
            55,
            456,
            57,
            454,
            58,
            454,
            58,
            454,
            58,
            454,
            58,
            454,
            58,
            454,
            58,
            454,
            58,
            454,
            58,
            454,
            58,
            454,
            58,
            454,
            58,
            454,
            58,
            454,
            58,
            454,
            58,
            454,
            58,
            454,
            58,
            454,
            58,
            454,
            58,
            454,
            58,
            454,
            58,
            454,
            58,
            454,
            58,
            454,
            58,
            454,
            58,
            454,
            58,
            454,
            58,
            454,
            58,
            454,
            58,
            454,
            58,
            454,
            58,
            454,
            58,
            454,
            58,
            454,
            58,
            454,
            58,
            454,
            58,
            454,
            58,
            454,
            58,
            454,
            58,
            454,
            58,
            454,
            58,
            454,
            58,
            454,
            58,
            454,
            58,
            454,
            58,
            454,
            58,
            454,
            58,
            454,
            58,
            454,
            58,
            454,
            58,
            454,
            58,
            454,
            58,
            454,
            58,
            454,
            58,
            454,
            58,
            454,
            58,
            454,
            58,
            454,
            58,
            454,
            58,
            454,
            58,
            454,
            58,
            454,
            58,
            454,
            58,
            454,
            58,
            454,
            58,
            454,
            58,
            454,
            58,
            454,
            58,
            454,
            58,
            454,
            58,
            454,
            58,
            454,
            58,
            454,
            58,
            454,
            58,
            454,
            58,
            454,
            58,
            454,
            58,
            454,
            58,
            454,
            58,
            454,
            58,
            454,
            58,
            454,
            58,
            454,
            58,
            454,
            58,
            454,
            58,
            454,
            58,
            454,
            58,
            454,
            58,
            454,
            58,
            454,
            58,
            454,
            58,
            454,
            58,
            454,
            58,
            454,
            58,
            454,
            58,
            454,
            58,
            454,
            58,
            454,
            58,
            454,
            58,
            454,
            58,
            454,
            58,
            454,
            58,
            454,
            58,
            454,
            58,
            454,
            58,
            454,
            58,
            454,
            58,
            454,
            58,
            454,
            58,
            454,
            58,
            454,
            58,
            454,
            58,
            454,
            58,
            454,
            58,
            454,
            58,
            454,
            58,
            454,
            58,
            454,
            58,
            454,
            58,
            454,
            58,
            454,
            58,
            454,
            58,
            454,
            58,
            454,
            58,
            454,
            58,
            454,
            58,
            454,
            58,
            454,
            58,
            454,
            58,
            454,
            58,
            454,
            57,
            455,
            57,
            455,
            57,
            455,
            56,
            456,
            56,
            456,
            56,
            456,
            56,
            456,
            55,
            457,
            55,
            457,
            54,
            458,
            53,
            459,
            53,
            459,
            52,
            460,
            52,
            460,
            51,
            461,
            51,
            461,
            50,
            462,
            49,
            463,
            47,
            465,
            47,
            480,
            28,
            488,
            24,
            491,
            21,
            500,
            12,
            502,
            10,
            506,
            5,
            101150
          ],
          "format": "uncompressed_rle"
        },
        "method": "geometric_taxonomy",
        "crop_file": "C:\\Users\\netta\\OneDrive\\Documents\\Coding Projects\\3D renderer and segmenter\\output\\segmenter\\HAD95_3579_1\\part_crops\\shoulder\\HAD95_3579_1_phi_320_theta_100__shoulder.png"
      },
      {
        "part_name": "body",
        "confidence": 0.85,
        "low_confidence": false,
        "quality_score": 0.925,
        "bbox_xywh": [
          143,
          208,
          222,
          171
        ],
        "mask_area_px": 24310,
        "mask_rle": {
          "size": [
            512,
            512
          ],
          "counts": [
            73426,
            7,
            505,
            11,
            501,
            14,
            496,
            18,
            494,
            20,
            492,
            21,
            491,
            23,
            489,
            24,
            488,
            26,
            486,
            26,
            486,
            28,
            484,
            29,
            483,
            30,
            482,
            31,
            481,
            32,
            480,
            33,
            479,
            34,
            478,
            35,
            477,
            35,
            477,
            36,
            476,
            38,
            474,
            38,
            474,
            39,
            473,
            39,
            473,
            40,
            472,
            40,
            472,
            41,
            471,
            41,
            471,
            41,
            471,
            42,
            47,
            19,
            404,
            43,
            42,
            28,
            399,
            43,
            28,
            45,
            396,
            44,
            15,
            61,
            392,
            122,
            390,
            125,
            387,
            128,
            384,
            130,
            382,
            132,
            380,
            134,
            378,
            136,
            376,
            138,
            374,
            140,
            372,
            141,
            371,
            143,
            369,
            145,
            367,
            146,
            366,
            148,
            364,
            149,
            363,
            151,
            361,
            153,
            359,
            155,
            357,
            157,
            355,
            158,
            354,
            160,
            352,
            161,
            351,
            162,
            350,
            164,
            348,
            165,
            347,
            166,
            346,
            167,
            345,
            168,
            344,
            169,
            343,
            170,
            342,
            171,
            341,
            171,
            341,
            171,
            341,
            171,
            341,
            171,
            341,
            171,
            341,
            171,
            341,
            171,
            341,
            171,
            341,
            171,
            341,
            171,
            341,
            171,
            341,
            171,
            341,
            171,
            341,
            171,
            341,
            171,
            341,
            171,
            341,
            171,
            341,
            171,
            341,
            171,
            341,
            171,
            341,
            171,
            341,
            171,
            341,
            171,
            341,
            171,
            341,
            171,
            341,
            171,
            341,
            171,
            341,
            171,
            341,
            171,
            341,
            171,
            341,
            171,
            341,
            171,
            341,
            171,
            341,
            171,
            341,
            171,
            341,
            171,
            341,
            171,
            341,
            171,
            341,
            171,
            341,
            171,
            341,
            171,
            341,
            171,
            341,
            171,
            341,
            171,
            341,
            171,
            341,
            171,
            341,
            171,
            341,
            171,
            341,
            171,
            341,
            171,
            341,
            171,
            341,
            171,
            341,
            171,
            341,
            171,
            341,
            171,
            341,
            171,
            341,
            171,
            341,
            171,
            341,
            171,
            341,
            171,
            341,
            171,
            341,
            171,
            341,
            171,
            341,
            171,
            341,
            171,
            341,
            171,
            341,
            171,
            341,
            171,
            341,
            171,
            341,
            171,
            341,
            171,
            341,
            171,
            341,
            171,
            341,
            171,
            341,
            171,
            341,
            39,
            9,
            123,
            341,
            39,
            13,
            119,
            341,
            38,
            17,
            116,
            341,
            37,
            20,
            114,
            341,
            36,
            23,
            112,
            341,
            35,
            24,
            112,
            341,
            34,
            26,
            111,
            341,
            33,
            29,
            109,
            341,
            33,
            31,
            107,
            341,
            33,
            32,
            106,
            341,
            32,
            35,
            104,
            341,
            32,
            38,
            101,
            341,
            32,
            40,
            99,
            341,
            32,
            43,
            96,
            341,
            31,
            45,
            95,
            341,
            31,
            48,
            92,
            341,
            30,
            53,
            88,
            341,
            29,
            56,
            86,
            341,
            29,
            57,
            85,
            341,
            28,
            60,
            83,
            341,
            28,
            61,
            82,
            341,
            27,
            64,
            80,
            341,
            27,
            66,
            78,
            341,
            26,
            68,
            77,
            341,
            25,
            69,
            77,
            341,
            23,
            72,
            76,
            341,
            23,
            74,
            74,
            341,
            19,
            79,
            73,
            341,
            19,
            81,
            71,
            341,
            19,
            82,
            70,
            348,
            12,
            83,
            69,
            350,
            10,
            84,
            68,
            354,
            5,
            87,
            66,
            447,
            65,
            448,
            64,
            450,
            62,
            451,
            61,
            453,
            59,
            454,
            58,
            456,
            56,
            457,
            55,
            458,
            54,
            459,
            53,
            460,
            52,
            461,
            51,
            463,
            49,
            463,
            49,
            464,
            48,
            466,
            46,
            467,
            45,
            468,
            44,
            469,
            43,
            469,
            43,
            471,
            41,
            472,
            40,
            473,
            39,
            473,
            39,
            474,
            38,
            476,
            36,
            476,
            36,
            478,
            34,
            479,
            33,
            480,
            32,
            481,
            31,
            482,
            30,
            484,
            28,
            486,
            26,
            489,
            23,
            494,
            18,
            496,
            16,
            498,
            14,
            499,
            13,
            500,
            12,
            502,
            10,
            503,
            9,
            504,
            8,
            505,
            7,
            506,
            6,
            507,
            5,
            508,
            4,
            509,
            3,
            510,
            2,
            511,
            1,
            75397
          ],
          "format": "uncompressed_rle"
        },
        "method": "geometric_taxonomy",
        "crop_file": "C:\\Users\\netta\\OneDrive\\Documents\\Coding Projects\\3D renderer and segmenter\\output\\segmenter\\HAD95_3579_1\\part_crops\\body\\HAD95_3579_1_phi_320_theta_100__body.png"
      },
      {
        "part_name": "base",
        "confidence": 0.6573,
        "low_confidence": false,
        "quality_score": 0.8286,
        "bbox_xywh": [
          198,
          369,
          175,
          62
        ],
        "mask_area_px": 7446,
        "mask_rle": {
          "size": [
            512,
            512
          ],
          "counts": [
            101745,
            1,
            511,
            3,
            509,
            4,
            508,
            5,
            507,
            6,
            506,
            7,
            505,
            8,
            504,
            9,
            503,
            10,
            502,
            11,
            501,
            12,
            500,
            12,
            500,
            13,
            499,
            14,
            498,
            14,
            498,
            15,
            497,
            16,
            496,
            17,
            495,
            18,
            494,
            18,
            494,
            19,
            493,
            20,
            492,
            21,
            491,
            22,
            490,
            23,
            489,
            23,
            489,
            24,
            488,
            25,
            487,
            25,
            487,
            25,
            487,
            26,
            486,
            27,
            485,
            28,
            484,
            28,
            484,
            29,
            483,
            30,
            482,
            30,
            482,
            31,
            481,
            32,
            480,
            32,
            480,
            33,
            479,
            34,
            478,
            34,
            478,
            34,
            478,
            35,
            477,
            36,
            476,
            36,
            476,
            37,
            475,
            37,
            475,
            38,
            474,
            38,
            474,
            39,
            473,
            39,
            473,
            40,
            472,
            40,
            472,
            41,
            471,
            41,
            471,
            42,
            470,
            42,
            470,
            43,
            469,
            43,
            469,
            44,
            468,
            44,
            468,
            44,
            468,
            45,
            467,
            45,
            467,
            46,
            466,
            46,
            466,
            46,
            466,
            47,
            465,
            47,
            465,
            48,
            464,
            48,
            464,
            48,
            464,
            49,
            463,
            49,
            463,
            50,
            462,
            50,
            462,
            50,
            462,
            51,
            461,
            51,
            461,
            51,
            461,
            51,
            461,
            51,
            461,
            51,
            461,
            52,
            460,
            52,
            460,
            53,
            459,
            53,
            459,
            54,
            458,
            54,
            458,
            54,
            458,
            55,
            457,
            55,
            457,
            55,
            457,
            55,
            457,
            55,
            457,
            55,
            457,
            55,
            457,
            55,
            457,
            55,
            457,
            57,
            455,
            57,
            455,
            57,
            455,
            58,
            454,
            58,
            454,
            58,
            454,
            59,
            453,
            59,
            453,
            59,
            453,
            59,
            453,
            59,
            453,
            60,
            452,
            60,
            452,
            60,
            452,
            60,
            452,
            60,
            452,
            61,
            451,
            61,
            451,
            61,
            451,
            61,
            451,
            61,
            451,
            61,
            451,
            61,
            451,
            62,
            450,
            62,
            450,
            62,
            450,
            62,
            450,
            62,
            450,
            62,
            450,
            62,
            450,
            62,
            450,
            62,
            450,
            62,
            450,
            62,
            450,
            62,
            450,
            62,
            450,
            62,
            450,
            62,
            450,
            62,
            450,
            62,
            450,
            62,
            450,
            62,
            450,
            61,
            451,
            61,
            451,
            61,
            451,
            61,
            451,
            60,
            452,
            60,
            452,
            59,
            453,
            59,
            453,
            58,
            454,
            57,
            455,
            55,
            457,
            54,
            458,
            53,
            459,
            52,
            460,
            50,
            463,
            48,
            465,
            46,
            467,
            43,
            470,
            39,
            474,
            37,
            476,
            35,
            478,
            34,
            479,
            32,
            481,
            30,
            483,
            28,
            485,
            25,
            489,
            20,
            493,
            18,
            495,
            16,
            497,
            14,
            499,
            12,
            501,
            9,
            71284
          ],
          "format": "uncompressed_rle"
        },
        "method": "geometric_taxonomy",
        "crop_file": "C:\\Users\\netta\\OneDrive\\Documents\\Coding Projects\\3D renderer and segmenter\\output\\segmenter\\HAD95_3579_1\\part_crops\\base\\HAD95_3579_1_phi_320_theta_100__base.png"
      },
      {
        "part_name": "foot",
        "confidence": 0.5695,
        "low_confidence": false,
        "quality_score": 0.7142,
        "bbox_xywh": [
          220,
          389,
          153,
          42
        ],
        "mask_area_px": 4293,
        "mask_rle": {
          "size": [
            512,
            512
          ],
          "counts": [
            113029,
            1,
            511,
            2,
            510,
            3,
            509,
            3,
            509,
            4,
            508,
            5,
            507,
            5,
            507,
            5,
            507,
            6,
            506,
            7,
            505,
            8,
            504,
            8,
            504,
            9,
            503,
            10,
            502,
            10,
            502,
            11,
            501,
            12,
            500,
            12,
            500,
            13,
            499,
            14,
            498,
            14,
            498,
            14,
            498,
            15,
            497,
            16,
            496,
            16,
            496,
            17,
            495,
            17,
            495,
            18,
            494,
            18,
            494,
            19,
            493,
            19,
            493,
            20,
            492,
            20,
            492,
            21,
            491,
            21,
            491,
            22,
            490,
            22,
            490,
            23,
            489,
            23,
            489,
            24,
            488,
            24,
            488,
            24,
            488,
            25,
            487,
            25,
            487,
            26,
            486,
            26,
            486,
            26,
            486,
            27,
            485,
            27,
            485,
            28,
            484,
            28,
            484,
            28,
            484,
            29,
            483,
            29,
            483,
            30,
            482,
            30,
            482,
            30,
            482,
            31,
            481,
            31,
            481,
            31,
            481,
            31,
            481,
            31,
            481,
            31,
            481,
            32,
            480,
            32,
            480,
            33,
            479,
            33,
            479,
            34,
            478,
            34,
            478,
            34,
            478,
            35,
            477,
            35,
            477,
            35,
            477,
            35,
            477,
            35,
            477,
            35,
            477,
            35,
            477,
            35,
            477,
            35,
            477,
            37,
            475,
            37,
            475,
            37,
            475,
            38,
            474,
            38,
            474,
            38,
            474,
            39,
            473,
            39,
            473,
            39,
            473,
            39,
            473,
            39,
            473,
            40,
            472,
            40,
            472,
            40,
            472,
            40,
            472,
            40,
            472,
            41,
            471,
            41,
            471,
            41,
            471,
            41,
            471,
            41,
            471,
            41,
            471,
            41,
            471,
            42,
            470,
            42,
            470,
            42,
            470,
            42,
            470,
            42,
            470,
            42,
            470,
            42,
            470,
            42,
            470,
            42,
            470,
            42,
            470,
            42,
            470,
            42,
            470,
            42,
            470,
            42,
            470,
            42,
            470,
            42,
            470,
            42,
            470,
            42,
            470,
            42,
            470,
            41,
            471,
            41,
            471,
            41,
            471,
            41,
            471,
            40,
            472,
            40,
            472,
            39,
            473,
            39,
            473,
            38,
            474,
            37,
            475,
            35,
            477,
            34,
            478,
            33,
            479,
            32,
            480,
            30,
            482,
            29,
            483,
            28,
            484,
            26,
            486,
            23,
            489,
            22,
            490,
            21,
            491,
            21,
            491,
            20,
            492,
            19,
            493,
            18,
            494,
            16,
            496,
            13,
            499,
            12,
            500,
            11,
            501,
            10,
            502,
            9,
            503,
            7,
            71284
          ],
          "format": "uncompressed_rle"
        },
        "method": "geometric_taxonomy",
        "crop_file": "C:\\Users\\netta\\OneDrive\\Documents\\Coding Projects\\3D renderer and segmenter\\output\\segmenter\\HAD95_3579_1\\part_crops\\foot\\HAD95_3579_1_phi_320_theta_100__foot.png"
      },
      {
        "part_name": "handle",
        "confidence": 0.7892,
        "low_confidence": false,
        "quality_score": 0.8946,
        "bbox_xywh": [
          143,
          156,
          199,
          189
        ],
        "mask_area_px": 12185,
        "mask_rle": {
          "size": [
            512,
            512
          ],
          "counts": [
            73426,
            7,
            505,
            11,
            501,
            14,
            492,
            22,
            488,
            26,
            485,
            28,
            481,
            33,
            478,
            35,
            475,
            39,
            472,
            40,
            470,
            44,
            467,
            46,
            465,
            48,
            463,
            50,
            461,
            52,
            458,
            55,
            456,
            57,
            454,
            59,
            452,
            60,
            451,
            62,
            449,
            65,
            447,
            65,
            446,
            67,
            445,
            67,
            444,
            69,
            442,
            70,
            441,
            72,
            440,
            72,
            439,
            73,
            438,
            75,
            47,
            19,
            370,
            77,
            42,
            28,
            365,
            77,
            28,
            45,
            361,
            79,
            15,
            61,
            356,
            158,
            353,
            162,
            348,
            167,
            342,
            172,
            336,
            178,
            329,
            185,
            326,
            188,
            324,
            189,
            323,
            189,
            323,
            189,
            323,
            189,
            323,
            189,
            323,
            189,
            323,
            189,
            323,
            189,
            323,
            189,
            323,
            189,
            323,
            189,
            323,
            189,
            323,
            189,
            323,
            189,
            323,
            189,
            323,
            189,
            323,
            189,
            323,
            189,
            323,
            189,
            323,
            189,
            323,
            189,
            323,
            189,
            323,
            189,
            323,
            189,
            323,
            189,
            323,
            189,
            323,
            189,
            323,
            189,
            323,
            189,
            323,
            189,
            323,
            189,
            323,
            189,
            323,
            189,
            323,
            189,
            323,
            189,
            40259,
            83,
            45,
            61,
            323,
            83,
            48,
            58,
            323,
            82,
            53,
            54,
            323,
            81,
            56,
            52,
            323,
            81,
            57,
            51,
            323,
            80,
            60,
            49,
            323,
            80,
            61,
            48,
            323,
            79,
            64,
            46,
            323,
            79,
            66,
            44,
            323,
            78,
            68,
            43,
            323,
            77,
            69,
            43,
            323,
            75,
            72,
            42,
            323,
            75,
            74,
            40,
            323,
            26,
            17,
            28,
            79,
            39,
            323,
            14,
            33,
            24,
            81,
            37,
            323,
            12,
            38,
            21,
            82,
            36,
            323,
            11,
            48,
            12,
            83,
            35,
            323,
            10,
            51,
            10,
            84,
            34,
            323,
            9,
            56,
            5,
            87,
            32,
            323,
            8,
            150,
            31,
            323,
            6,
            153,
            30,
            323,
            5,
            156,
            28,
            323,
            3,
            159,
            27,
            323,
            2,
            162,
            25,
            488,
            24,
            490,
            22,
            491,
            21,
            492,
            20,
            493,
            19,
            494,
            18,
            495,
            17,
            497,
            15,
            497,
            15,
            498,
            14,
            500,
            12,
            501,
            11,
            502,
            10,
            503,
            9,
            503,
            9,
            505,
            7,
            506,
            6,
            507,
            5,
            507,
            5,
            508,
            4,
            510,
            2,
            510,
            2,
            87207
          ],
          "format": "uncompressed_rle"
        },
        "method": "geometric_taxonomy",
        "crop_file": "C:\\Users\\netta\\OneDrive\\Documents\\Coding Projects\\3D renderer and segmenter\\output\\segmenter\\HAD95_3579_1\\part_crops\\handle\\HAD95_3579_1_phi_320_theta_100__handle.png"
      },
      {
        "part_name": "spout",
        "confidence": 0.6158,
        "low_confidence": false,
        "quality_score": 0.8079,
        "bbox_xywh": [
          146,
          105,
          185,
          103
        ],
        "mask_area_px": 5955,
        "mask_rle": {
          "size": [
            512,
            512
          ],
          "counts": [
            74956,
            4,
            506,
            6,
            505,
            7,
            502,
            10,
            501,
            11,
            499,
            13,
            498,
            14,
            496,
            16,
            495,
            17,
            494,
            18,
            493,
            19,
            492,
            20,
            490,
            22,
            489,
            23,
            488,
            24,
            487,
            25,
            486,
            26,
            485,
            27,
            485,
            27,
            484,
            28,
            484,
            28,
            483,
            29,
            482,
            30,
            481,
            31,
            481,
            31,
            480,
            32,
            479,
            33,
            478,
            34,
            478,
            34,
            477,
            35,
            476,
            36,
            475,
            37,
            473,
            39,
            470,
            42,
            466,
            46,
            461,
            51,
            457,
            55,
            455,
            57,
            451,
            61,
            448,
            64,
            446,
            66,
            443,
            69,
            441,
            71,
            439,
            73,
            437,
            75,
            436,
            76,
            434,
            78,
            432,
            80,
            432,
            80,
            432,
            80,
            423,
            89,
            421,
            91,
            417,
            95,
            414,
            98,
            412,
            100,
            410,
            102,
            409,
            103,
            409,
            103,
            409,
            103,
            409,
            103,
            409,
            103,
            409,
            103,
            409,
            103,
            409,
            103,
            409,
            103,
            409,
            103,
            409,
            103,
            409,
            103,
            409,
            103,
            409,
            103,
            409,
            103,
            409,
            103,
            40354,
            94,
            419,
            93,
            419,
            93,
            420,
            92,
            421,
            91,
            421,
            91,
            422,
            90,
            422,
            90,
            423,
            89,
            424,
            88,
            424,
            88,
            425,
            87,
            425,
            87,
            426,
            60,
            17,
            9,
            427,
            47,
            33,
            5,
            427,
            45,
            38,
            2,
            428,
            43,
            469,
            42,
            471,
            40,
            473,
            38,
            474,
            36,
            477,
            34,
            479,
            31,
            481,
            30,
            483,
            27,
            486,
            25,
            487,
            24,
            489,
            22,
            490,
            20,
            493,
            17,
            496,
            14,
            498,
            13,
            500,
            11,
            502,
            8,
            504,
            6,
            93043
          ],
          "format": "uncompressed_rle"
        },
        "method": "geometric_taxonomy",
        "crop_file": "C:\\Users\\netta\\OneDrive\\Documents\\Coding Projects\\3D renderer and segmenter\\output\\segmenter\\HAD95_3579_1\\part_crops\\spout\\HAD95_3579_1_phi_320_theta_100__spout.png"
      }
    ]
  }
}