{
  "schema_version": "0.1",
  "artifact_id": "HAD95_3579_1",
  "artifact_class": "pottery",
  "image": {
    "image_filename": "HAD95_3579_1__phi_040__theta_040.png",
    "image_path": "C:\\Users\\netta\\OneDrive\\Documents\\Coding Projects\\3D renderer and segmenter\\output\\images\\unclassified\\HAD95_3579_1\\HAD95_3579_1__phi_040__theta_040.png",
    "angle_metadata": {
      "phi": 40,
      "theta": 40,
      "elevation": null
    },
    "width": 512,
    "height": 512,
    "annotated_file": "C:\\Users\\netta\\OneDrive\\Documents\\Coding Projects\\3D renderer and segmenter\\output\\segmenter\\HAD95_3579_1\\annotated\\HAD95_3579_1_phi_040_theta_040__annotated.png",
    "clean_visual_file": "C:\\Users\\netta\\OneDrive\\Documents\\Coding Projects\\3D renderer and segmenter\\output\\segmenter\\HAD95_3579_1\\clean_visual\\HAD95_3579_1_phi_040_theta_040__clean.png",
    "parts": [
      {
        "part_name": "rim",
        "confidence": 0.5242,
        "low_confidence": true,
        "quality_score": 0.6045,
        "bbox_xywh": [
          183,
          108,
          107,
          37
        ],
        "mask_area_px": 2248,
        "mask_rle": {
          "size": [
            512,
            512
          ],
          "counts": [
            93809,
            5,
            505,
            8,
            503,
            11,
            500,
            12,
            500,
            13,
            499,
            14,
            497,
            16,
            496,
            17,
            495,
            17,
            495,
            18,
            494,
            19,
            494,
            19,
            493,
            19,
            493,
            20,
            492,
            21,
            491,
            22,
            490,
            23,
            489,
            24,
            488,
            26,
            486,
            27,
            485,
            28,
            484,
            28,
            484,
            29,
            483,
            30,
            483,
            30,
            482,
            35,
            477,
            35,
            477,
            35,
            477,
            35,
            477,
            35,
            478,
            34,
            478,
            34,
            478,
            34,
            478,
            34,
            478,
            34,
            479,
            33,
            479,
            33,
            479,
            33,
            479,
            33,
            480,
            32,
            480,
            32,
            480,
            32,
            480,
            32,
            481,
            31,
            481,
            31,
            481,
            31,
            482,
            30,
            482,
            30,
            483,
            29,
            483,
            29,
            483,
            29,
            484,
            28,
            484,
            28,
            484,
            28,
            485,
            27,
            485,
            27,
            485,
            27,
            486,
            26,
            486,
            26,
            487,
            25,
            487,
            25,
            488,
            24,
            488,
            24,
            488,
            24,
            489,
            23,
            489,
            23,
            489,
            23,
            490,
            22,
            490,
            22,
            490,
            22,
            491,
            21,
            492,
            20,
            492,
            20,
            492,
            20,
            493,
            19,
            493,
            19,
            494,
            18,
            494,
            18,
            495,
            17,
            495,
            17,
            496,
            16,
            496,
            16,
            497,
            15,
            497,
            15,
            498,
            14,
            498,
            14,
            499,
            13,
            499,
            13,
            500,
            12,
            500,
            12,
            501,
            11,
            502,
            10,
            502,
            10,
            503,
            9,
            503,
            9,
            504,
            8,
            504,
            8,
            505,
            7,
            506,
            6,
            506,
            6,
            507,
            5,
            508,
            4,
            508,
            4,
            509,
            3,
            510,
            2,
            511,
            1,
            511,
            1,
            114031
          ],
          "format": "uncompressed_rle"
        },
        "method": "geometric_taxonomy",
        "crop_file": "C:\\Users\\netta\\OneDrive\\Documents\\Coding Projects\\3D renderer and segmenter\\output\\segmenter\\HAD95_3579_1\\part_crops\\rim\\HAD95_3579_1_phi_040_theta_040__rim.png"
      },
      {
        "part_name": "neck",
        "confidence": 0.6562,
        "low_confidence": false,
        "quality_score": 0.8281,
        "bbox_xywh": [
          183,
          145,
          165,
          50
        ],
        "mask_area_px": 6252,
        "mask_rle": {
          "size": [
            512,
            512
          ],
          "counts": [
            93866,
            6,
            505,
            9,
            502,
            10,
            501,
            12,
            498,
            14,
            497,
            15,
            496,
            17,
            495,
            17,
            494,
            19,
            492,
            20,
            491,
            22,
            489,
            24,
            487,
            25,
            486,
            27,
            485,
            28,
            483,
            29,
            483,
            30,
            481,
            31,
            480,
            33,
            478,
            35,
            476,
            36,
            475,
            38,
            474,
            38,
            474,
            39,
            472,
            40,
            467,
            45,
            467,
            46,
            466,
            47,
            465,
            47,
            465,
            48,
            464,
            49,
            463,
            49,
            463,
            49,
            463,
            50,
            462,
            50,
            462,
            50,
            462,
            50,
            462,
            50,
            462,
            50,
            462,
            50,
            462,
            50,
            462,
            50,
            462,
            50,
            462,
            50,
            462,
            50,
            462,
            50,
            462,
            50,
            462,
            50,
            462,
            50,
            462,
            50,
            462,
            50,
            462,
            50,
            462,
            50,
            462,
            50,
            462,
            50,
            462,
            50,
            462,
            50,
            462,
            50,
            462,
            50,
            462,
            50,
            462,
            50,
            462,
            50,
            462,
            50,
            462,
            50,
            462,
            50,
            462,
            50,
            462,
            50,
            462,
            50,
            462,
            50,
            462,
            50,
            462,
            50,
            462,
            50,
            462,
            50,
            462,
            50,
            462,
            50,
            462,
            50,
            462,
            50,
            462,
            50,
            462,
            50,
            462,
            50,
            462,
            50,
            462,
            50,
            462,
            50,
            462,
            50,
            462,
            50,
            462,
            50,
            462,
            50,
            462,
            50,
            462,
            50,
            462,
            50,
            462,
            50,
            462,
            50,
            462,
            50,
            462,
            50,
            462,
            50,
            462,
            50,
            462,
            50,
            462,
            50,
            462,
            50,
            462,
            50,
            462,
            50,
            462,
            50,
            462,
            50,
            462,
            50,
            462,
            50,
            462,
            50,
            462,
            50,
            462,
            50,
            463,
            49,
            463,
            49,
            464,
            48,
            465,
            47,
            466,
            46,
            466,
            46,
            467,
            45,
            468,
            44,
            469,
            43,
            469,
            43,
            470,
            42,
            471,
            41,
            472,
            40,
            473,
            39,
            474,
            38,
            474,
            38,
            475,
            37,
            476,
            36,
            477,
            35,
            478,
            34,
            479,
            33,
            479,
            33,
            480,
            32,
            481,
            31,
            482,
            30,
            483,
            29,
            484,
            28,
            485,
            27,
            485,
            27,
            486,
            26,
            487,
            25,
            488,
            24,
            488,
            24,
            489,
            23,
            490,
            22,
            491,
            21,
            491,
            21,
            492,
            20,
            493,
            19,
            494,
            18,
            495,
            17,
            496,
            16,
            497,
            15,
            498,
            14,
            499,
            13,
            499,
            13,
            501,
            11,
            501,
            11,
            503,
            9,
            504,
            8,
            505,
            7,
            506,
            6,
            507,
            5,
            508,
            4,
            509,
            3,
            510,
            2,
            511,
            1,
            84285
          ],
          "format": "uncompressed_rle"
        },
        "method": "geometric_taxonomy",
        "crop_file": "C:\\Users\\netta\\OneDrive\\Documents\\Coding Projects\\3D renderer and segmenter\\output\\segmenter\\HAD95_3579_1\\part_crops\\neck\\HAD95_3579_1_phi_040_theta_040__neck.png"
      },
      {
        "part_name": "shoulder",
        "confidence": 0.6875,
        "low_confidence": false,
        "quality_score": 0.8437,
        "bbox_xywh": [
          217,
          195,
          163,
          53
        ],
        "mask_area_px": 7199,
        "mask_rle": {
          "size": [
            512,
            512
          ],
          "counts": [
            111299,
            1,
            50,
            2,
            459,
            1,
            49,
            3,
            459,
            1,
            48,
            4,
            459,
            2,
            45,
            6,
            459,
            2,
            44,
            7,
            459,
            2,
            42,
            9,
            459,
            3,
            39,
            11,
            459,
            3,
            38,
            12,
            459,
            4,
            35,
            14,
            459,
            4,
            33,
            16,
            459,
            4,
            31,
            18,
            459,
            4,
            30,
            19,
            459,
            4,
            28,
            21,
            459,
            5,
            26,
            22,
            459,
            5,
            24,
            24,
            459,
            5,
            23,
            25,
            459,
            5,
            21,
            27,
            459,
            5,
            19,
            29,
            459,
            5,
            18,
            30,
            459,
            5,
            17,
            31,
            459,
            7,
            13,
            33,
            459,
            7,
            11,
            35,
            459,
            8,
            9,
            36,
            459,
            53,
            459,
            53,
            459,
            53,
            459,
            53,
            459,
            53,
            459,
            53,
            459,
            53,
            459,
            53,
            459,
            53,
            459,
            53,
            459,
            53,
            459,
            53,
            459,
            53,
            459,
            53,
            459,
            53,
            459,
            53,
            459,
            53,
            459,
            53,
            459,
            53,
            459,
            53,
            459,
            53,
            459,
            53,
            459,
            53,
            459,
            53,
            459,
            53,
            459,
            53,
            459,
            53,
            459,
            53,
            459,
            53,
            459,
            53,
            459,
            53,
            459,
            53,
            459,
            53,
            459,
            53,
            459,
            53,
            459,
            53,
            459,
            53,
            459,
            53,
            459,
            53,
            459,
            53,
            459,
            53,
            459,
            53,
            459,
            53,
            459,
            53,
            459,
            53,
            459,
            53,
            459,
            53,
            459,
            53,
            459,
            53,
            459,
            53,
            459,
            53,
            459,
            53,
            459,
            53,
            459,
            53,
            459,
            53,
            459,
            53,
            459,
            53,
            459,
            53,
            459,
            53,
            459,
            53,
            459,
            53,
            459,
            53,
            459,
            53,
            459,
            53,
            459,
            53,
            459,
            53,
            459,
            53,
            459,
            53,
            459,
            53,
            459,
            53,
            459,
            53,
            459,
            53,
            459,
            53,
            459,
            53,
            459,
            53,
            459,
            53,
            459,
            53,
            459,
            53,
            459,
            53,
            459,
            53,
            459,
            53,
            459,
            53,
            459,
            53,
            459,
            53,
            459,
            53,
            459,
            53,
            459,
            53,
            459,
            53,
            459,
            53,
            459,
            53,
            459,
            53,
            459,
            53,
            459,
            53,
            459,
            53,
            459,
            53,
            459,
            53,
            459,
            53,
            459,
            53,
            459,
            53,
            459,
            53,
            459,
            53,
            459,
            53,
            459,
            53,
            459,
            53,
            459,
            53,
            459,
            53,
            459,
            53,
            459,
            53,
            460,
            52,
            461,
            51,
            462,
            50,
            463,
            49,
            464,
            48,
            466,
            46,
            467,
            45,
            468,
            44,
            470,
            42,
            471,
            41,
            473,
            39,
            474,
            38,
            475,
            37,
            477,
            35,
            479,
            33,
            480,
            32,
            482,
            30,
            483,
            29,
            485,
            27,
            487,
            25,
            488,
            24,
            490,
            22,
            492,
            20,
            494,
            18,
            496,
            16,
            498,
            14,
            500,
            12,
            502,
            10,
            504,
            8,
            506,
            6,
            508,
            4,
            510,
            2,
            67848
          ],
          "format": "uncompressed_rle"
        },
        "method": "geometric_taxonomy",
        "crop_file": "C:\\Users\\netta\\OneDrive\\Documents\\Coding Projects\\3D renderer and segmenter\\output\\segmenter\\HAD95_3579_1\\part_crops\\shoulder\\HAD95_3579_1_phi_040_theta_040__shoulder.png"
      },
      {
        "part_name": "body",
        "confidence": 0.85,
        "low_confidence": false,
        "quality_score": 0.925,
        "bbox_xywh": [
          186,
          217,
          196,
          156
        ],
        "mask_area_px": 22927,
        "mask_rle": {
          "size": [
            512,
            512
          ],
          "counts": [
            95521,
            5,
            507,
            5,
            507,
            6,
            506,
            7,
            505,
            7,
            505,
            7,
            23,
            5,
            471,
            24,
            12,
            5,
            470,
            27,
            10,
            5,
            468,
            44,
            468,
            44,
            468,
            44,
            468,
            53,
            459,
            54,
            451,
            61,
            450,
            62,
            447,
            65,
            446,
            66,
            445,
            67,
            444,
            68,
            443,
            69,
            442,
            70,
            441,
            81,
            430,
            82,
            428,
            84,
            427,
            85,
            426,
            86,
            424,
            94,
            417,
            104,
            406,
            108,
            402,
            112,
            397,
            115,
            395,
            117,
            394,
            118,
            393,
            119,
            391,
            131,
            380,
            132,
            378,
            134,
            376,
            136,
            375,
            137,
            373,
            139,
            371,
            141,
            369,
            143,
            368,
            144,
            366,
            146,
            365,
            147,
            363,
            149,
            362,
            150,
            360,
            152,
            358,
            154,
            357,
            155,
            356,
            156,
            356,
            156,
            356,
            156,
            356,
            156,
            356,
            156,
            356,
            156,
            356,
            156,
            356,
            156,
            356,
            156,
            356,
            156,
            356,
            156,
            356,
            156,
            356,
            156,
            356,
            156,
            356,
            156,
            356,
            156,
            356,
            156,
            356,
            156,
            356,
            156,
            356,
            156,
            356,
            156,
            356,
            156,
            356,
            156,
            356,
            156,
            356,
            156,
            356,
            156,
            356,
            156,
            356,
            156,
            356,
            156,
            356,
            156,
            356,
            156,
            356,
            156,
            356,
            156,
            356,
            156,
            356,
            156,
            356,
            156,
            356,
            156,
            356,
            156,
            356,
            156,
            356,
            156,
            356,
            156,
            356,
            156,
            356,
            156,
            356,
            156,
            356,
            156,
            356,
            156,
            356,
            156,
            356,
            156,
            356,
            156,
            356,
            156,
            356,
            156,
            356,
            156,
            356,
            156,
            356,
            156,
            356,
            156,
            356,
            156,
            356,
            156,
            356,
            156,
            356,
            156,
            356,
            156,
            356,
            156,
            356,
            156,
            356,
            156,
            356,
            156,
            356,
            156,
            356,
            156,
            356,
            156,
            356,
            156,
            356,
            156,
            356,
            156,
            356,
            156,
            356,
            156,
            356,
            156,
            356,
            156,
            356,
            156,
            356,
            156,
            356,
            156,
            356,
            156,
            356,
            156,
            356,
            156,
            356,
            156,
            356,
            156,
            356,
            156,
            356,
            156,
            356,
            156,
            356,
            156,
            356,
            156,
            356,
            156,
            356,
            156,
            356,
            156,
            356,
            156,
            356,
            156,
            356,
            156,
            356,
            156,
            356,
            153,
            359,
            151,
            361,
            150,
            362,
            146,
            366,
            144,
            368,
            141,
            371,
            138,
            374,
            136,
            376,
            134,
            378,
            133,
            379,
            126,
            386,
            126,
            386,
            123,
            389,
            120,
            392,
            116,
            396,
            113,
            399,
            109,
            403,
            105,
            407,
            101,
            411,
            95,
            417,
            89,
            423,
            83,
            429,
            77,
            435,
            72,
            440,
            63,
            449,
            41,
            471,
            41,
            471,
            41,
            471,
            41,
            471,
            41,
            471,
            41,
            471,
            41,
            471,
            41,
            471,
            41,
            472,
            41,
            472,
            41,
            473,
            39,
            475,
            37,
            476,
            36,
            478,
            35,
            479,
            33,
            481,
            32,
            482,
            30,
            484,
            28,
            486,
            26,
            488,
            24,
            490,
            21,
            493,
            18,
            496,
            15,
            499,
            13,
            502,
            9,
            505,
            7,
            66814
          ],
          "format": "uncompressed_rle"
        },
        "method": "geometric_taxonomy",
        "crop_file": "C:\\Users\\netta\\OneDrive\\Documents\\Coding Projects\\3D renderer and segmenter\\output\\segmenter\\HAD95_3579_1\\part_crops\\body\\HAD95_3579_1_phi_040_theta_040__body.png"
      },
      {
        "part_name": "base",
        "confidence": 0.6122,
        "low_confidence": false,
        "quality_score": 0.8061,
        "bbox_xywh": [
          220,
          363,
          113,
          57
        ],
        "mask_area_px": 4917,
        "mask_rle": {
          "size": [
            512,
            512
          ],
          "counts": [
            113003,
            11,
            501,
            13,
            499,
            16,
            496,
            18,
            494,
            19,
            493,
            21,
            491,
            24,
            488,
            26,
            486,
            29,
            483,
            32,
            480,
            35,
            477,
            39,
            473,
            45,
            467,
            46,
            466,
            47,
            465,
            47,
            465,
            47,
            465,
            48,
            464,
            48,
            464,
            48,
            464,
            48,
            464,
            48,
            464,
            48,
            464,
            48,
            464,
            48,
            464,
            49,
            463,
            49,
            463,
            49,
            463,
            49,
            463,
            49,
            463,
            49,
            463,
            49,
            463,
            49,
            463,
            49,
            463,
            50,
            462,
            50,
            462,
            50,
            462,
            50,
            462,
            50,
            462,
            50,
            462,
            50,
            462,
            51,
            461,
            51,
            461,
            51,
            461,
            51,
            461,
            51,
            461,
            52,
            460,
            52,
            460,
            52,
            460,
            52,
            460,
            52,
            460,
            52,
            460,
            52,
            460,
            52,
            460,
            52,
            460,
            52,
            460,
            53,
            459,
            53,
            459,
            53,
            459,
            54,
            458,
            54,
            458,
            54,
            458,
            55,
            457,
            55,
            457,
            55,
            457,
            55,
            457,
            55,
            457,
            55,
            457,
            55,
            457,
            55,
            457,
            55,
            457,
            56,
            456,
            56,
            456,
            56,
            456,
            57,
            455,
            57,
            455,
            57,
            455,
            57,
            455,
            57,
            455,
            57,
            455,
            57,
            455,
            57,
            455,
            56,
            456,
            55,
            457,
            54,
            458,
            52,
            460,
            51,
            461,
            50,
            462,
            49,
            463,
            47,
            465,
            45,
            467,
            44,
            468,
            42,
            470,
            40,
            472,
            38,
            474,
            37,
            475,
            34,
            478,
            33,
            479,
            32,
            480,
            31,
            481,
            30,
            482,
            28,
            484,
            27,
            485,
            25,
            487,
            22,
            490,
            20,
            492,
            18,
            494,
            15,
            497,
            11,
            501,
            10,
            502,
            7,
            505,
            5,
            507,
            4,
            91793
          ],
          "format": "uncompressed_rle"
        },
        "method": "geometric_taxonomy",
        "crop_file": "C:\\Users\\netta\\OneDrive\\Documents\\Coding Projects\\3D renderer and segmenter\\output\\segmenter\\HAD95_3579_1\\part_crops\\base\\HAD95_3579_1_phi_040_theta_040__base.png"
      },
      {
        "part_name": "foot",
        "confidence": 0.544,
        "low_confidence": true,
        "quality_score": 0.6526,
        "bbox_xywh": [
          225,
          382,
          101,
          38
        ],
        "mask_area_px": 2851,
        "mask_rle": {
          "size": [
            512,
            512
          ],
          "counts": [
            115582,
            2,
            510,
            5,
            507,
            7,
            505,
            10,
            502,
            13,
            499,
            16,
            496,
            20,
            492,
            26,
            486,
            27,
            485,
            28,
            484,
            28,
            484,
            28,
            484,
            29,
            483,
            29,
            483,
            29,
            483,
            29,
            483,
            29,
            483,
            29,
            483,
            29,
            483,
            29,
            483,
            30,
            482,
            30,
            482,
            30,
            482,
            30,
            482,
            30,
            482,
            30,
            482,
            30,
            482,
            30,
            482,
            30,
            482,
            31,
            481,
            31,
            481,
            31,
            481,
            31,
            481,
            31,
            481,
            31,
            481,
            31,
            481,
            32,
            480,
            32,
            480,
            32,
            480,
            32,
            480,
            32,
            480,
            33,
            479,
            33,
            479,
            33,
            479,
            33,
            479,
            33,
            479,
            33,
            479,
            33,
            479,
            33,
            479,
            33,
            479,
            33,
            479,
            34,
            478,
            34,
            478,
            34,
            478,
            35,
            477,
            35,
            477,
            35,
            477,
            36,
            476,
            36,
            476,
            36,
            476,
            36,
            476,
            36,
            476,
            36,
            476,
            36,
            476,
            36,
            476,
            36,
            476,
            37,
            475,
            37,
            475,
            37,
            475,
            38,
            474,
            38,
            474,
            38,
            474,
            38,
            474,
            38,
            474,
            38,
            474,
            38,
            474,
            38,
            474,
            37,
            475,
            36,
            476,
            35,
            477,
            33,
            479,
            32,
            480,
            31,
            481,
            30,
            482,
            28,
            484,
            26,
            486,
            25,
            487,
            23,
            489,
            21,
            491,
            19,
            493,
            18,
            494,
            15,
            497,
            14,
            498,
            13,
            499,
            12,
            500,
            11,
            501,
            9,
            503,
            8,
            504,
            6,
            506,
            3,
            509,
            1,
            95361
          ],
          "format": "uncompressed_rle"
        },
        "method": "geometric_taxonomy",
        "crop_file": "C:\\Users\\netta\\OneDrive\\Documents\\Coding Projects\\3D renderer and segmenter\\output\\segmenter\\HAD95_3579_1\\part_crops\\foot\\HAD95_3579_1_phi_040_theta_040__foot.png"
      },
      {
        "part_name": "handle",
        "confidence": 0.85,
        "low_confidence": false,
        "quality_score": 0.925,
        "bbox_xywh": [
          183,
          170,
          199,
          172
        ],
        "mask_area_px": 13834,
        "mask_rle": {
          "size": [
            512,
            512
          ],
          "counts": [
            93866,
            6,
            506,
            8,
            504,
            8,
            504,
            9,
            110,
            5,
            388,
            9,
            110,
            5,
            388,
            9,
            110,
            6,
            387,
            10,
            109,
            7,
            386,
            10,
            109,
            7,
            386,
            11,
            108,
            7,
            23,
            5,
            358,
            11,
            102,
            24,
            12,
            5,
            358,
            12,
            100,
            27,
            10,
            5,
            358,
            13,
            97,
            44,
            358,
            13,
            97,
            44,
            358,
            14,
            96,
            44,
            358,
            15,
            95,
            53,
            349,
            15,
            95,
            54,
            348,
            16,
            87,
            61,
            348,
            16,
            86,
            62,
            348,
            17,
            82,
            65,
            348,
            18,
            80,
            66,
            348,
            18,
            79,
            67,
            348,
            19,
            77,
            68,
            348,
            19,
            76,
            69,
            348,
            20,
            74,
            70,
            348,
            20,
            73,
            79,
            340,
            20,
            72,
            80,
            340,
            21,
            69,
            82,
            340,
            22,
            67,
            83,
            340,
            22,
            66,
            84,
            340,
            23,
            63,
            86,
            340,
            24,
            61,
            87,
            340,
            24,
            59,
            89,
            340,
            24,
            57,
            91,
            340,
            25,
            53,
            94,
            340,
            26,
            50,
            96,
            340,
            26,
            49,
            97,
            340,
            26,
            48,
            98,
            340,
            27,
            45,
            100,
            340,
            27,
            44,
            101,
            340,
            27,
            42,
            103,
            340,
            28,
            39,
            105,
            340,
            28,
            38,
            106,
            340,
            29,
            35,
            108,
            340,
            29,
            33,
            110,
            340,
            29,
            31,
            112,
            340,
            29,
            30,
            113,
            340,
            29,
            28,
            115,
            340,
            30,
            26,
            116,
            340,
            30,
            24,
            118,
            340,
            30,
            23,
            119,
            340,
            30,
            21,
            121,
            340,
            30,
            19,
            123,
            340,
            30,
            18,
            124,
            340,
            30,
            17,
            125,
            340,
            32,
            13,
            127,
            340,
            32,
            11,
            129,
            340,
            33,
            9,
            130,
            340,
            172,
            340,
            172,
            340,
            172,
            340,
            172,
            340,
            172,
            340,
            172,
            340,
            172,
            340,
            172,
            34644,
            172,
            340,
            172,
            340,
            172,
            340,
            172,
            340,
            172,
            340,
            172,
            340,
            172,
            341,
            171,
            341,
            171,
            342,
            170,
            343,
            169,
            344,
            168,
            344,
            168,
            345,
            167,
            346,
            166,
            347,
            165,
            348,
            164,
            349,
            163,
            350,
            162,
            351,
            161,
            352,
            160,
            352,
            160,
            354,
            158,
            354,
            158,
            356,
            156,
            357,
            155,
            358,
            154,
            359,
            151,
            362,
            147,
            366,
            142,
            371,
            138,
            375,
            133,
            380,
            128,
            386,
            122,
            391,
            115,
            398,
            108,
            405,
            101,
            412,
            94,
            420,
            87,
            426,
            77,
            436,
            54,
            460,
            52,
            461,
            51,
            463,
            49,
            464,
            48,
            465,
            47,
            467,
            45,
            469,
            43,
            470,
            42,
            472,
            41,
            472,
            41,
            473,
            39,
            475,
            37,
            476,
            36,
            478,
            35,
            479,
            33,
            481,
            32,
            482,
            30,
            484,
            28,
            486,
            26,
            488,
            24,
            490,
            21,
            493,
            18,
            496,
            15,
            499,
            13,
            502,
            9,
            505,
            7,
            66814
          ],
          "format": "uncompressed_rle"
        },
        "method": "geometric_taxonomy",
        "crop_file": "C:\\Users\\netta\\OneDrive\\Documents\\Coding Projects\\3D renderer and segmenter\\output\\segmenter\\HAD95_3579_1\\part_crops\\handle\\HAD95_3579_1_phi_040_theta_040__handle.png"
      },
      {
        "part_name": "spout",
        "confidence": 0.627,
        "low_confidence": false,
        "quality_score": 0.8135,
        "bbox_xywh": [
          183,
          123,
          181,
          94
        ],
        "mask_area_px": 5367,
        "mask_rle": {
          "size": [
            512,
            512
          ],
          "counts": [
            93866,
            6,
            505,
            9,
            502,
            10,
            501,
            12,
            498,
            14,
            497,
            15,
            456,
            1,
            39,
            17,
            455,
            2,
            38,
            17,
            455,
            2,
            37,
            19,
            454,
            3,
            35,
            20,
            454,
            4,
            33,
            22,
            453,
            5,
            31,
            24,
            452,
            5,
            30,
            25,
            452,
            6,
            28,
            27,
            451,
            7,
            27,
            28,
            450,
            8,
            25,
            29,
            450,
            9,
            24,
            30,
            449,
            10,
            22,
            31,
            449,
            12,
            19,
            33,
            448,
            13,
            17,
            35,
            447,
            14,
            15,
            36,
            447,
            14,
            14,
            38,
            446,
            15,
            13,
            38,
            446,
            16,
            12,
            39,
            445,
            17,
            10,
            40,
            445,
            67,
            445,
            68,
            444,
            69,
            443,
            69,
            443,
            70,
            442,
            71,
            441,
            71,
            441,
            71,
            441,
            72,
            440,
            73,
            439,
            73,
            439,
            73,
            439,
            74,
            438,
            74,
            438,
            74,
            438,
            75,
            437,
            75,
            437,
            76,
            436,
            76,
            436,
            76,
            436,
            76,
            436,
            76,
            436,
            77,
            435,
            77,
            435,
            77,
            435,
            77,
            435,
            77,
            435,
            77,
            435,
            77,
            435,
            79,
            13,
            2,
            418,
            79,
            11,
            4,
            418,
            80,
            9,
            5,
            418,
            94,
            418,
            94,
            418,
            94,
            418,
            94,
            418,
            94,
            418,
            94,
            418,
            94,
            418,
            94,
            34764,
            52,
            461,
            51,
            462,
            50,
            463,
            49,
            463,
            49,
            464,
            48,
            465,
            47,
            466,
            46,
            466,
            46,
            467,
            45,
            468,
            44,
            469,
            43,
            469,
            43,
            470,
            42,
            471,
            41,
            472,
            40,
            473,
            39,
            474,
            38,
            475,
            37,
            476,
            36,
            477,
            35,
            477,
            35,
            479,
            33,
            479,
            33,
            481,
            31,
            482,
            30,
            483,
            29,
            484,
            28,
            485,
            27,
            486,
            26,
            487,
            25,
            488,
            24,
            489,
            23,
            491,
            21,
            492,
            20,
            493,
            19,
            494,
            18,
            495,
            17,
            497,
            15,
            498,
            14,
            499,
            13,
            501,
            11,
            502,
            10,
            504,
            8,
            505,
            7,
            506,
            6,
            508,
            4,
            510,
            2,
            511,
            1,
            76071
          ],
          "format": "uncompressed_rle"
        },
        "method": "geometric_taxonomy",
        "crop_file": "C:\\Users\\netta\\OneDrive\\Documents\\Coding Projects\\3D renderer and segmenter\\output\\segmenter\\HAD95_3579_1\\part_crops\\spout\\HAD95_3579_1_phi_040_theta_040__spout.png"
      }
    ]
  }
}